datapackage_pipelines_elasticsearch/VERSION
datapackage_pipelines_elasticsearch/__init__.py
datapackage_pipelines_elasticsearch/processors/__init__.py
datapackage_pipelines_elasticsearch/processors/dump/__init__.py
datapackage_pipelines_elasticsearch/processors/dump/to_index.py
datapackage_pipelines_elasticsearch-0.0.14.dist-info/LICENSE.md
datapackage_pipelines_elasticsearch-0.0.14.dist-info/METADATA
datapackage_pipelines_elasticsearch-0.0.14.dist-info/WHEEL
datapackage_pipelines_elasticsearch-0.0.14.dist-info/top_level.txt
datapackage_pipelines_elasticsearch-0.0.14.dist-info/RECORD
