Metadata-Version: 2.1
Name: datapackage-pipelines-elasticsearch
Version: 0.0.14
Summary: {{ DESCRIPTION }}
Home-page: https://github.com/frictionlessdata/datapackage-pipelines-elasticsearch
Author: Open Knowledge International
License: MIT
Keywords: data,analytics
Platform: UNKNOWN
Classifier: Development Status :: 4 - Beta
Classifier: Environment :: Web Environment
Classifier: Intended Audience :: Developers
Classifier: License :: OSI Approved :: MIT License
Classifier: Operating System :: OS Independent
Classifier: Programming Language :: Python :: 3.6
Classifier: Topic :: Internet :: WWW/HTTP :: Dynamic Content
Classifier: Topic :: Software Development :: Libraries :: Python Modules
Requires-Dist: datapackage-pipelines (>=1.1.1)
Requires-Dist: tableschema-elasticsearch (>=0.4.0)
Provides-Extra: develop
Requires-Dist: pylama ; extra == 'develop'
Requires-Dist: tox ; extra == 'develop'
